github_tui
