Metadata-Version: 2.1
Name: github-tui
Version: 0.1.6
Summary: Github TUI for issues, notifications, discussions, and PR management
Home-page: https://github.com/costrouc/github-tui
Author: Christopher Ostrouchov
Author-email: chris.ostrouchov@gmail.com
License: BSD License
Project-URL: Bug Reports, https://github.com/costrouc/github-tui
Project-URL: Documentation, https://github.com/quansight/conda-store
Project-URL: Source, https://conda-store.readthedocs.io/
Keywords: github tui
Classifier: Development Status :: 3 - Alpha
Classifier: Intended Audience :: Developers
Classifier: Topic :: Software Development :: Build Tools
Classifier: License :: OSI Approved :: BSD License
Classifier: Programming Language :: Python :: 3
Classifier: Programming Language :: Python :: 3.7
Classifier: Programming Language :: Python :: 3.8
Classifier: Programming Language :: Python :: 3.9
Classifier: Programming Language :: Python :: 3 :: Only
Provides-Extra: dev
License-File: LICENSE
